yamtam/__init__.py
yamtam/colors.py
yamtam/yamtam.py
yamtam-0.1.0.dist-info/LICENSE
yamtam-0.1.0.dist-info/METADATA
yamtam-0.1.0.dist-info/WHEEL
yamtam-0.1.0.dist-info/entry_points.txt
yamtam-0.1.0.dist-info/top_level.txt
yamtam-0.1.0.dist-info/RECORD
