Metadata-Version: 2.1
Name: yamtam
Version: 0.1.0
Summary: CLI utility for parsing data from yamtam.nyc
Home-page: http://github.com/tolidano/yamtam
Author: Shawn Tolidano
Author-email: Shawn Tolidano <shawn@yamtam.nyc>
License: Copyright 2024 yamtam
Project-URL: Homepage, https://github.com/tolidano/yamtam
Project-URL: Issues, https://github.com/tolidano/yamtam
Classifier: Programming Language :: Python :: 3
Classifier: License :: OSI Approved :: MIT License
Classifier: Operating System :: OS Independent
Requires-Python: >=3.10
License-File: LICENSE
